buffalo/__init__.py
buffalo/buffalo.py
buffalo/exceptions.py
buffalo/project.py
buffalo/utils.py
buffalo/work.py
buffalo/templates/wf_template.yml
buffalo_workflow-0.1.7.dist-info/METADATA
buffalo_workflow-0.1.7.dist-info/WHEEL
buffalo_workflow-0.1.7.dist-info/licenses/LICENSE
buffalo_workflow-0.1.7.dist-info/RECORD
