Metadata-Version: 2.4
Name: buffalo_workflow
Version: 0.1.7
Summary: A workflow automation tool
Project-URL: Homepage, https://github.com/wengzhiwen/buffalo
Project-URL: Bug Tracker, https://github.com/wengzhiwen/buffalo/issues
Author-email: James Weng <wengzhiwen@gmail.com>
License: MIT License
License-File: LICENSE
Classifier: License :: OSI Approved :: MIT License
Classifier: Operating System :: OS Independent
Classifier: Programming Language :: Python :: 3
Requires-Python: >=3.8
Requires-Dist: pyyaml>=5.1
